resipy/DCA.py
resipy/Project.py
resipy/SelectPoints.py
resipy/Settings.py
resipy/Survey.py
resipy/__init__.py
resipy/gmshWrap.py
resipy/interpolation.py
resipy/meshTools.py
resipy/meshTools_working.py
resipy/parsers.py
resipy/protocol.py
resipy/r2help.py
resipy/r2in.py
resipy/saveData.py
resipy/seqGen.py
resipy/sliceMesh.py
resipy/template.py
resipy/cext/cbuild.py
resipy/cext/fastRecip.c
resipy/cext/fastRecip.cp310-win_amd64.pyd
resipy/cext/fastRecip.cp311-win_amd64.pyd
resipy/cext/fastRecip.cp312-win_amd64.pyd
resipy/cext/fastRecip.cp313-win_amd64.pyd
resipy/cext/fastRecip.cp36-win_amd64.pyd
resipy/cext/fastRecip.cp37-win_amd64.pyd
resipy/cext/fastRecip.cp38-win_amd64.pyd
resipy/cext/fastRecip.cp39-win_amd64.pyd
resipy/cext/fastRecip.cpython-310-x86_64-linux-gnu.so
resipy/cext/fastRecip.cpython-311-darwin.so
resipy/cext/fastRecip.cpython-311-x86_64-linux-gnu.so
resipy/cext/fastRecip.cpython-312-darwin.so
resipy/cext/fastRecip.cpython-312-x86_64-linux-gnu.so
resipy/cext/fastRecip.cpython-312-x86_64-linux-gnu.so.orig
resipy/cext/fastRecip.cpython-313-darwin.so
resipy/cext/fastRecip.cpython-36m-x86_64-linux-gnu.so
resipy/cext/fastRecip.cpython-37m-x86_64-linux-gnu.so
resipy/cext/fastRecip.cpython-38-x86_64-linux-gnu.so
resipy/cext/fastRecip.cpython-39-x86_64-linux-gnu.so
resipy/cext/fastRecip.pyx
resipy/cext/meshCalc.cp310-win_amd64.pyd
resipy/cext/meshCalc.cp311-win_amd64.pyd
resipy/cext/meshCalc.cp312-win_amd64.pyd
resipy/cext/meshCalc.cp313-win_amd64.pyd
resipy/cext/meshCalc.cp36-win_amd64.pyd
resipy/cext/meshCalc.cp37-win_amd64.pyd
resipy/cext/meshCalc.cp38-win_amd64.pyd
resipy/cext/meshCalc.cp39-win_amd64.pyd
resipy/cext/meshCalc.cpython-310-darwin.so
resipy/cext/meshCalc.cpython-310-x86_64-linux-gnu.so
resipy/cext/meshCalc.cpython-311-arm-linux-gnueabihf.so
resipy/cext/meshCalc.cpython-311-darwin.so
resipy/cext/meshCalc.cpython-311-x86_64-linux-gnu.so
resipy/cext/meshCalc.cpython-312-darwin.so
resipy/cext/meshCalc.cpython-312-x86_64-linux-gnu.so
resipy-3.6.3.dist-info/LICENSE
resipy-3.6.3.dist-info/METADATA
resipy-3.6.3.dist-info/WHEEL
resipy-3.6.3.dist-info/top_level.txt
resipy-3.6.3.dist-info/RECORD
