Metadata-Version: 2.1
Name: resipy
Version: 3.6.3
Summary: API for resistivity and IP inversion/modelling around R* codes
Home-page: https://gitlab.com/hkex/resipy
Author: HKEx
Classifier: Programming Language :: Python :: 3
Classifier: License :: OSI Approved :: GNU General Public License v3 (GPLv3)
Classifier: Operating System :: OS Independent
License-File: LICENSE
Requires-Dist: numpy<2.0.0
Requires-Dist: matplotlib
Requires-Dist: pandas
Requires-Dist: scipy
Requires-Dist: requests
Requires-Dist: psutil
Requires-Dist: chardet
